MANIFEST.in
README.txt
setup.py
collective/__init__.py
collective.relateditems.egg-info/PKG-INFO
collective.relateditems.egg-info/SOURCES.txt
collective.relateditems.egg-info/dependency_links.txt
collective.relateditems.egg-info/entry_points.txt
collective.relateditems.egg-info/namespace_packages.txt
collective.relateditems.egg-info/not-zip-safe
collective.relateditems.egg-info/paster_plugins.txt
collective.relateditems.egg-info/requires.txt
collective.relateditems.egg-info/top_level.txt
collective/relateditems/__init__.py
collective/relateditems/configure.zcml
collective/relateditems/document_relateditems.pt
collective/relateditems/interfaces.py
collective/relateditems/relateditems.py
collective/relateditems/tests.py
docs/HISTORY.txt
docs/INSTALL.txt
docs/LICENSE.GPL
docs/LICENSE.txt