Metadata-Version: 1.0
Name: collective.relateditems
Version: 0.1.0
Summary: Backporting Plone 4 related items viewlet into Plone 3
Home-page: http://plone.org/products/collective.relateditems
Author: Luca Fabbri
Author-email: luca@keul.it
License: GPL
Keywords: plone related-items backport viewlet
Platform: UNKNOWN
Classifier: Framework :: Plone
Classifier: Framework :: Plone :: 3.3
Classifier: Programming Language :: Python
Classifier: Development Status :: 4 - Beta
